onm/__init__.py
onm-0.0.1.dist-info/LICENSE
onm-0.0.1.dist-info/METADATA
onm-0.0.1.dist-info/WHEEL
onm-0.0.1.dist-info/top_level.txt
onm-0.0.1.dist-info/RECORD
